py_fakename-0.2.dist-info/RECORD
py_fakename-0.2.dist-info/METADATA
py_fakename-0.2.dist-info/metadata.json
py_fakename-0.2.dist-info/DESCRIPTION.rst
py_fakename-0.2.dist-info/top_level.txt
py_fakename-0.2.dist-info/WHEEL
fakename/six.py
fakename/wrapper.py
fakename/__init__.py
